az_evgrid_pydantic_schema/__init__.py
az_evgrid_pydantic_schema/base.py
az_evgrid_pydantic_schema/storage_blob.py
az_evgrid_pydantic_schema-0.2.0.dist-info/LICENSE
az_evgrid_pydantic_schema-0.2.0.dist-info/WHEEL
az_evgrid_pydantic_schema-0.2.0.dist-info/METADATA
az_evgrid_pydantic_schema-0.2.0.dist-info/RECORD
